pulumi_sumologic/__init__.py
pulumi_sumologic/_inputs.py
pulumi_sumologic/_utilities.py
pulumi_sumologic/app.py
pulumi_sumologic/aws_inventory_source.py
pulumi_sumologic/aws_xray_source.py
pulumi_sumologic/azure_event_hub_log_source.py
pulumi_sumologic/azure_metrics_source.py
pulumi_sumologic/cloud_syslog_source.py
pulumi_sumologic/cloud_to_cloud_source.py
pulumi_sumologic/cloudfront_source.py
pulumi_sumologic/cloudtrail_source.py
pulumi_sumologic/cloudwatch_source.py
pulumi_sumologic/collector.py
pulumi_sumologic/connection.py
pulumi_sumologic/content.py
pulumi_sumologic/content_permission.py
pulumi_sumologic/cse_aggregation_rule.py
pulumi_sumologic/cse_automation.py
pulumi_sumologic/cse_chain_rule.py
pulumi_sumologic/cse_context_action.py
pulumi_sumologic/cse_custom_entity_type.py
pulumi_sumologic/cse_custom_insight.py
pulumi_sumologic/cse_custom_match_list_column.py
pulumi_sumologic/cse_entity_criticality_config.py
pulumi_sumologic/cse_entity_entity_group_configuration.py
pulumi_sumologic/cse_entity_normalization_configuration.py
pulumi_sumologic/cse_first_seen_rule.py
pulumi_sumologic/cse_insights_configuration.py
pulumi_sumologic/cse_insights_resolution.py
pulumi_sumologic/cse_insights_status.py
pulumi_sumologic/cse_inventory_entity_group_configuration.py
pulumi_sumologic/cse_log_mapping.py
pulumi_sumologic/cse_match_list.py
pulumi_sumologic/cse_match_rule.py
pulumi_sumologic/cse_network_block.py
pulumi_sumologic/cse_outlier_rule.py
pulumi_sumologic/cse_rule_tuning_expression.py
pulumi_sumologic/cse_tag_schema.py
pulumi_sumologic/cse_threshold_rule.py
pulumi_sumologic/dashboard.py
pulumi_sumologic/data_forwarding_destination.py
pulumi_sumologic/data_forwarding_rule.py
pulumi_sumologic/elb_source.py
pulumi_sumologic/field.py
pulumi_sumologic/field_extraction_rule.py
pulumi_sumologic/folder.py
pulumi_sumologic/gcp_metrics_source.py
pulumi_sumologic/gcp_source.py
pulumi_sumologic/get_admin_recommended_folder.py
pulumi_sumologic/get_apps.py
pulumi_sumologic-1.0.11.dist-info/METADATA
pulumi_sumologic-1.0.11.dist-info/WHEEL
pulumi_sumologic-1.0.11.dist-info/top_level.txt
pulumi_sumologic-1.0.11.dist-info/RECORD
